tradepose_models/__init__.py
tradepose_models/base.py
tradepose_models/enums.py
tradepose_models/schemas.py
tradepose_models/shared.py
tradepose_models/types.py
tradepose_models/validators.py
tradepose_models/auth/__init__.py
tradepose_models/auth/api_keys.py
tradepose_models/auth/auth.py
tradepose_models/billing/__init__.py
tradepose_models/billing/checkout.py
tradepose_models/billing/plans.py
tradepose_models/billing/subscriptions.py
tradepose_models/billing/usage.py
tradepose_models/broker/__init__.py
tradepose_models/broker/account_config.py
tradepose_models/broker/account_models.py
tradepose_models/broker/binding.py
tradepose_models/broker/connection_status.py
tradepose_models/datafeed/__init__.py
tradepose_models/datafeed/events.py
tradepose_models/enums/__init__.py
tradepose_models/enums/account_source.py
tradepose_models/enums/action_type.py
tradepose_models/enums/broker_type.py
tradepose_models/enums/currency.py
tradepose_models/enums/engagement_phase.py
tradepose_models/enums/execution_mode.py
tradepose_models/enums/exit_reason.py
tradepose_models/enums/export_type.py
tradepose_models/enums/fill_type.py
tradepose_models/enums/freq.py
tradepose_models/enums/indicator_type.py
tradepose_models/enums/operation_type.py
tradepose_models/enums/order_side.py
tradepose_models/enums/order_status.py
tradepose_models/enums/order_strategy.py
tradepose_models/enums/order_type.py
tradepose_models/enums/orderbook_event_type.py
tradepose_models/enums/persist_mode.py
tradepose_models/enums/reject_reason.py
tradepose_models/enums/risk_method.py
tradepose_models/enums/stream.py
tradepose_models/enums/task_status.py
tradepose_models/enums/time_in_force.py
tradepose_models/enums/trade_direction.py
tradepose_models/enums/trend_type.py
tradepose_models/enums/weekday.py
tradepose_models/enums/write_origin.py
tradepose_models/events/__init__.py
tradepose_models/events/order_events.py
tradepose_models/events/trade_events.py
tradepose_models/export/__init__.py
tradepose_models-1.4.0.dist-info/METADATA
tradepose_models-1.4.0.dist-info/WHEEL
tradepose_models-1.4.0.dist-info/RECORD
