Metadata-Version: 2.4
Name: tradepose-models
Version: 1.4.0
Summary: Shared Pydantic models for TradePose platform
Author-email: TradePose Team <codeotter0201@gmail.com>
License: MIT
Keywords: models,pydantic,trading
Classifier: Development Status :: 4 - Beta
Classifier: Intended Audience :: Developers
Classifier: License :: OSI Approved :: MIT License
Classifier: Operating System :: OS Independent
Classifier: Programming Language :: Python :: 3
Classifier: Programming Language :: Python :: 3.13
Classifier: Topic :: Software Development :: Libraries :: Python Modules
Requires-Python: >=3.13
Requires-Dist: polars
Requires-Dist: pydantic>=2.12.1
